rokh/__init__.py
rokh/errors.py
rokh/functions.py
rokh/params.py
rokh/events/__init__.py
rokh/events/gregorian.py
rokh/events/hijri.py
rokh/events/jalali.py
rokh-0.3.dist-info/licenses/AUTHORS.md
rokh-0.3.dist-info/licenses/LICENSE
rokh-0.3.dist-info/METADATA
rokh-0.3.dist-info/WHEEL
rokh-0.3.dist-info/top_level.txt
rokh-0.3.dist-info/RECORD
